mcio_remote/__about__.py
mcio_remote/__init__.py
mcio_remote/config.py
mcio_remote/controller.py
mcio_remote/gui.py
mcio_remote/gym_lite.py
mcio_remote/instance.py
mcio_remote/mc_mock.py
mcio_remote/mcio_gui.py
mcio_remote/network.py
mcio_remote/py.typed
mcio_remote/server.py
mcio_remote/types.py
mcio_remote/util.py
mcio_remote/world.py
mcio_remote/envs/__init__.py
mcio_remote/envs/base_env.py
mcio_remote/envs/env_util.py
mcio_remote/envs/mcio_env.py
mcio_remote/envs/minerl_env.py
mcio_remote/scripts/README.md
mcio_remote/scripts/mcio_cmd.py
mcio_remote-0.6.1.dist-info/METADATA
mcio_remote-0.6.1.dist-info/WHEEL
mcio_remote-0.6.1.dist-info/entry_points.txt
mcio_remote-0.6.1.dist-info/licenses/LICENSE
mcio_remote-0.6.1.dist-info/RECORD
